README.md
setup.py
amazon_product_reviews_scraper/__init__.py
amazon_product_reviews_scraper.egg-info/PKG-INFO
amazon_product_reviews_scraper.egg-info/SOURCES.txt
amazon_product_reviews_scraper.egg-info/dependency_links.txt
amazon_product_reviews_scraper.egg-info/requires.txt
amazon_product_reviews_scraper.egg-info/top_level.txt