Metadata-Version: 2.1
Name: amazon-product-reviews-scraper
Version: 1.0.1
Summary: A python library to scrape product reviews data automatically on amazon.
Home-page: https://amazon-api.datakund.com/en/latest/
Author: DataKund
Author-email: datakund@gmail.com
License: Apache License 2.0
Keywords: amazon python bot_studio scraper reviews product data web-scraping
Platform: UNKNOWN
